finbourne_access/__init__.py
finbourne_access/api/__init__.py
finbourne_access/api/application_metadata_api.py
finbourne_access/api/policies_api.py
finbourne_access/api/policy_templates_api.py
finbourne_access/api/roles_api.py
finbourne_access/api/user_roles_api.py
finbourne_access/api_client.py
finbourne_access/api_response.py
finbourne_access/configuration.py
finbourne_access/exceptions.py
finbourne_access/extensions/__init__.py
finbourne_access/extensions/api_client.py
finbourne_access/extensions/api_client_factory.py
finbourne_access/extensions/api_configuration.py
finbourne_access/extensions/configuration_loaders.py
finbourne_access/extensions/configuration_options.py
finbourne_access/extensions/file_access_token.py
finbourne_access/extensions/proxy_config.py
finbourne_access/extensions/refreshing_token.py
finbourne_access/extensions/rest.py
finbourne_access/extensions/retry.py
finbourne_access/extensions/socket_keep_alive.py
finbourne_access/extensions/tcp_keep_alive_connector.py
finbourne_access/models/__init__.py
finbourne_access/models/access_controlled_action.py
finbourne_access/models/access_controlled_resource.py
finbourne_access/models/action_id.py
finbourne_access/models/add_policy_collection_to_role_request.py
finbourne_access/models/add_policy_to_role_request.py
finbourne_access/models/add_to_policy_collection_request.py
finbourne_access/models/as_at_predicate_contract.py
finbourne_access/models/as_at_range_for_spec.py
finbourne_access/models/as_at_relative.py
finbourne_access/models/attached_policy_definition_response.py
finbourne_access/models/date_quality.py
finbourne_access/models/date_unit.py
finbourne_access/models/effective_date_has_quality.py
finbourne_access/models/effective_date_relative.py
finbourne_access/models/effective_range.py
finbourne_access/models/entitlement_metadata.py
finbourne_access/models/evaluation_request.py
finbourne_access/models/evaluation_response.py
finbourne_access/models/evaluation_result.py
finbourne_access_sdk-2.4.1.dist-info/METADATA
finbourne_access_sdk-2.4.1.dist-info/WHEEL
finbourne_access_sdk-2.4.1.dist-info/RECORD
